odoo/addons/stock_service_level_route/README.rst
odoo/addons/stock_service_level_route/__init__.py
odoo/addons/stock_service_level_route/__manifest__.py
odoo/addons/stock_service_level_route/i18n/fr.po
odoo/addons/stock_service_level_route/i18n/it.po
odoo/addons/stock_service_level_route/i18n/stock_service_level_route.pot
odoo/addons/stock_service_level_route/models/__init__.py
odoo/addons/stock_service_level_route/models/procurement_group.py
odoo/addons/stock_service_level_route/models/stock_location_route.py
odoo/addons/stock_service_level_route/models/stock_service_level.py
odoo/addons/stock_service_level_route/readme/CONFIGURATION.rst
odoo/addons/stock_service_level_route/readme/CONTRIBUTORS.rst
odoo/addons/stock_service_level_route/readme/DESCRIPTION.rst
odoo/addons/stock_service_level_route/static/description/icon.png
odoo/addons/stock_service_level_route/static/description/index.html
odoo/addons/stock_service_level_route/tests/__init__.py
odoo/addons/stock_service_level_route/tests/test_stock_service_level_route.py
odoo/addons/stock_service_level_route/views/stock_location_route_views.xml
odoo/addons/stock_service_level_route/views/stock_service_level_views.xml
odoo14_addon_stock_service_level_route-14.0.1.0.1.dev4.dist-info/METADATA
odoo14_addon_stock_service_level_route-14.0.1.0.1.dev4.dist-info/WHEEL
odoo14_addon_stock_service_level_route-14.0.1.0.1.dev4.dist-info/top_level.txt
odoo14_addon_stock_service_level_route-14.0.1.0.1.dev4.dist-info/RECORD
