Metadata-Version: 2.1
Name: odoo14-addon-stock_service_level_route
Version: 14.0.1.0.1.dev4
Summary: Manage stock rules/routes by service level
Home-page: https://github.com/OCA/wms
Author: Pierre Verkest <pierreverkest84@gmail.com>, Odoo Community Association (OCA)
Author-email: support@odoo-community.org
License: AGPL-3
Classifier: Programming Language :: Python
Classifier: Framework :: Odoo
Classifier: Framework :: Odoo :: 14.0
Classifier: License :: OSI Approved :: GNU Affero General Public License v3
Classifier: Development Status :: 4 - Beta
Requires-Python: >=3.6
Requires-Dist: odoo14-addon-stock-service-level
Requires-Dist: odoo<14.1dev,>=14.0a
